<?xml version="1.0" encoding="utf-8" ?>
<LanguageData>
	
	<MentalBreakThreshold.label>Zusammenbruchschwelle</MentalBreakThreshold.label>
	<MentalBreakThreshold.description>So lange die Stimmung unterhalb dieser Schwelle ist, besteht die Gefahr eines Zusammenbruchs des Charkters.</MentalBreakThreshold.description>
	
	<PsychicSensitivity.label>Psychische Sensibilität</PsychicSensitivity.label>
	<PsychicSensitivity.description>Multiplikator für die Stärke von psychischen Phänomenen, die diesen Charakter beeinflussen.</PsychicSensitivity.description>
	
	<MoveSpeed.label>Bewegungsgeschwindigkeit</MoveSpeed.label>
	<MoveSpeed.description>Die Geschwindigkeit, mit der sich dieser Charakter durch die Welt bewegt. In Zellen pro Sekunde.</MoveSpeed.description>
	
</LanguageData>