<?xml version="1.0" encoding="UTF-8"?>
<LanguageData>

  <Spacer.label>Raumfahrer</Spacer.label>
  <Spacer.description>Leute aus den Tiefen des Weltalls.</Spacer.description>
  <Spacer.pawnsPlural>Raumfahrer</Spacer.pawnsPlural>
  <Spacer.fixedName>Raumfahrer</Spacer.fixedName>

  <SpacerHostile.label>Raumfahrer</SpacerHostile.label>
  <SpacerHostile.description>Leute aus den Tiefen des Weltalls.</SpacerHostile.description>
  <SpacerHostile.pawnsPlural>Raumfahrer</SpacerHostile.pawnsPlural>
  <SpacerHostile.fixedName>Raumfahrer</SpacerHostile.fixedName>

  <!-- Special sub-humanlike factions -->

  <Mechanoid.label>Mechanoiden Schwarm</Mechanoid.label>
  <Mechanoid.description>Ein Schwarm uralter Roboter mit der Fähigkeit, neue herzustellen.</Mechanoid.description>
  <Mechanoid.pawnsPlural>Mechanoiden</Mechanoid.pawnsPlural>
  <Mechanoid.fixedName>Ein Mechanoiden Schwarm</Mechanoid.fixedName>
  
  <Insect.label>Insekt</Insect.label>
  <Insect.description>Normalerweise aggressive und aufdringliche Insekten.</Insect.description>
  <Insect.pawnsPlural>Insekten</Insect.pawnsPlural>
  <Insect.fixedName>Insekten</Insect.fixedName>

</LanguageData>
