<?xml version="1.0" encoding="utf-8" ?>
<LanguageData>
	
  <rep>
    <path>MentalBreakPsychotic.rulePack.rulesStrings[0]</path>
    <trans>image->[pawn_nameFull] verfällt in rasende Wut [circumstance_phrase]. [psychotic_extra]</trans>
  </rep>
  <rep>
    <path>MentalBreakPsychotic.rulePack.rulesStrings[1]</path>
    <trans>image->[pawn_nameFull] wird gewalttätig und dreht durch [circumstance_phrase]. [psychotic_extra]</trans>
  </rep>
  <rep>
    <path>MentalBreakPsychotic.rulePack.rulesStrings[2]</path>
    <trans>image->[pawn_nameFull] stürzt mit einem irren Blick auf [pawn_possessive]em Gesicht vorwärts [circumstance_phrase]. [psychotic_extra]</trans>
  </rep>
  <rep>
    <path>MentalBreakPsychotic.rulePack.rulesStrings[3]</path>
    <trans>psychotic_extra->und schüttelt sich vor unbändiger Wut.</trans>
  </rep>
  <rep>
    <path>MentalBreakPsychotic.rulePack.rulesStrings[4]</path>
    <trans>psychotic_extra->[pawn_possessive]e Zähne sind zu einem tötlichen Knurren gefletscht.</trans>
  </rep>
  <rep>
    <path>MentalBreakPsychotic.rulePack.rulesStrings[5]</path>
    <trans>psychotic_extra->[pawn_possessive]e Augen sind tote Höhlen des Wahnsinns.</trans>
  </rep>
  <rep>
    <path>MentalBreakPsychotic.rulePack.rulesStrings[6]</path>
    <trans>psychotic_extra->Spucke fliegt aus [pawn_possessive]em Mund, als er [pawn_possessive]e wahnsinnige Wut hinausschreit.</trans>
  </rep>
  
	
  <rep>
    <path>MentalBreakGaveUp.rulePack.rulesStrings[0]</path>
    <trans>image->[pawn_nameFull] zerbricht an dem Stress und gibt auf [circumstance_phrase]. [gaveup_extra]</trans>
  </rep>
  <rep>
    <path>MentalBreakGaveUp.rulePack.rulesStrings[1]</path>
    <trans>image->[pawn_nameFull] weint unkontrolliert [circumstance_phrase]. [gaveup_extra]</trans>
  </rep>
  <rep>
    <path>MentalBreakGaveUp.rulePack.rulesStrings[2]</path>
    <trans>image->[pawn_nameFull] stolpert mit einem zerbrochenen Ausdruck auf [pawn_possessive]em Gesicht durch die Gegend [circumstance_phrase]. [gaveup_extra]</trans>
  </rep>
  <rep>
    <path>MentalBreakGaveUp.rulePack.rulesStrings[3]</path>
    <trans>gaveup_extra->[pawn_pronoun] Tränen ströhmen über [pawn_possessive] Gesicht.</trans>
  </rep>
  <rep>
    <path>MentalBreakGaveUp.rulePack.rulesStrings[4]</path>
    <trans>gaveup_extra->[pawn_pronoun] lacht aus den tiefsten Tiefen [pawn_possessive]er Depression.</trans>
  </rep>
  <rep>
    <path>MentalBreakGaveUp.rulePack.rulesStrings[5]</path>
    <trans>gaveup_extra->[pawn_nameShortDefinite] schaut Hilfe suchend gen Himmel.</trans>
  </rep>
  <rep>
    <path>MentalBreakGaveUp.rulePack.rulesStrings[6]</path>
    <trans>gaveup_extra->[pawn_pronoun] zerreißt [pawn_possessive]e eigene Kleidung.</trans>
  </rep>
  
	
</LanguageData>
