<?xml version="1.0" encoding="UTF-8"?>
<LanguageData>

  <!-- Plant products -->

  <Hay.label>Heu</Hay.label>
  <Hay.description>Nährstoffreiches Gras und Sprösslinge, geerntet und zur Lagerung verdichtet. Heu ist ein gutes Tierfutter, aber ungenießbar für Menschen.</Hay.description>

  <RawHops.label>Hopfen</RawHops.label>
  <RawHops.description>Roher Hopfen. Ein Aromastoff und Konservierungsmittel, das zum Herstellen von Bier benötigt wird.</RawHops.description>

  <!-- Raw foods -->

  <RawPotatoes.label>Kartoffeln</RawPotatoes.label>
  <RawPotatoes.description>Rohe Kartoffeln.</RawPotatoes.description>

  <RawRice.label>Reis</RawRice.label>
  <RawRice.description>Roher Reis.</RawRice.description>

  <RawAgave.label>Agavefrucht</RawAgave.label>
  <RawAgave.description>Rohe Früchte der Agave.</RawAgave.description>

  <RawCorn.label>Mais</RawCorn.label>
  <RawCorn.description>Roher Mais. Schmeckt lecker und ist roh genießbar.</RawCorn.description>

  <RawBerries.label>Beeren</RawBerries.label>
  <RawBerries.description>Verschiedene Beeren. Schmeckt lecker und ist roh genießbar.</RawBerries.description>

</LanguageData>
