<?xml version="1.0" encoding="UTF-8"?>
<LanguageData>

	<!-- Added body parts -->

	<PegLeg.label>Holzbein</PegLeg.label>
	<PegLeg.labelNoun>ein Holzbein</PegLeg.labelNoun>
	
	<WoodenFoot.label>Holzfuß</WoodenFoot.label>
	<WoodenFoot.labelNoun>ein Holzfuß</WoodenFoot.labelNoun>

	<Denture.label>Zahnprothese</Denture.label>
	<Denture.labelNoun>eine Zahnprothese</Denture.labelNoun>

	<SimpleProstheticLeg.label>Beinprothese</SimpleProstheticLeg.label>
	<SimpleProstheticLeg.labelNoun>eine Beinprothese</SimpleProstheticLeg.labelNoun>

	<SimpleProstheticArm.label>Armprothese</SimpleProstheticArm.label>
	<SimpleProstheticArm.labelNoun>eine Armprothese</SimpleProstheticArm.labelNoun>
	<SimpleProstheticArm.comps.0.tools.0.label>Faust</SimpleProstheticArm.comps.0.tools.0.label>

	<SimpleProstheticHeart.label>Herzprothese</SimpleProstheticHeart.label>
	<SimpleProstheticHeart.labelNoun>ein künstliches Herz</SimpleProstheticHeart.labelNoun>

	<BionicEye.label>Bionisches Auge</BionicEye.label>
	<BionicEye.labelNoun>ein bionisches Auge</BionicEye.labelNoun>

	<BionicArm.label>Bionischer Arm</BionicArm.label>
	<BionicArm.labelNoun>ein bionischer Arm</BionicArm.labelNoun>
	<BionicArm.comps.0.tools.0.label>Faust</BionicArm.comps.0.tools.0.label>

	<BionicLeg.label>Bionisches Bein</BionicLeg.label>
	<BionicLeg.labelNoun>ein bionisches Bein</BionicLeg.labelNoun>

	<BionicSpine.label>Bionische Wirbelsäule</BionicSpine.label>
	<BionicSpine.labelNoun>eine bionische Wirbelsäule</BionicSpine.labelNoun>

	<BionicHeart.label>Bionisches Herz</BionicHeart.label>
	<BionicHeart.labelNoun>ein bionisches Herz</BionicHeart.labelNoun>

	<BionicStomach.label>Bionischer Magen</BionicStomach.label>
	<BionicStomach.labelNoun>ein bionischer Magen</BionicStomach.labelNoun>

	<PowerClaw.label>Powerkralle</PowerClaw.label>
	<PowerClaw.labelNoun>eine Powerkralle</PowerClaw.labelNoun>
	<PowerClaw.comps.0.tools.0.label>Kralle</PowerClaw.comps.0.tools.0.label>
	
	<ArchotechEye.label>Archotech-Auge</ArchotechEye.label>
	<ArchotechEye.labelNoun>ein archotechnologisches Auge</ArchotechEye.labelNoun>
	
	<ArchotechArm.label>Archotech-Arm</ArchotechArm.label>
	<ArchotechArm.labelNoun>ein archotechnologischer Arm</ArchotechArm.labelNoun>
	<ArchotechArm.comps.0.tools.0.label>Faust</ArchotechArm.comps.0.tools.0.label>
	
	<ArchotechLeg.label>Archotech-Bein</ArchotechLeg.label>
	<ArchotechLeg.labelNoun>ein archotechnologisches Bein</ArchotechLeg.labelNoun>

</LanguageData>
