<?xml version="1.0" encoding="UTF-8"?>
<LanguageData>
  
  <!-- EN: anima tree -->
  <AnimaTreeSpawn.label>Anima-Baum</AnimaTreeSpawn.label>
  <!-- EN: Anima tree -->
  <AnimaTreeSpawn.letterLabel>Anima-Baum</AnimaTreeSpawn.letterLabel>
  <!-- EN: An anima tree has sprouted nearby.\n\nTribal peoples can use this as a powerful meditation focus, but only if artificial structures are not placed nearby. -->
  <AnimaTreeSpawn.letterText>Ein Anima-Baum ist in der Nähe erschienen.\n\nStammesvölker können diesen Baum als kraftvollen Meditationsfokus nutzen, aber nur, wenn keine künstlichen Strukturen in der Nähe platziert sind.</AnimaTreeSpawn.letterText>
  
  <!-- EN: tribute collector caravan arrival -->
  <CaravanArrivalTributeCollector.label>Tributeintreiberkarawane</CaravanArrivalTributeCollector.label>
  
</LanguageData>