<?xml version="1.0" encoding="UTF-8"?>
<LanguageData>
  
  <!-- EN: chinchilla -->
  <Chinchilla.label>Chinchilla</Chinchilla.label>
  <Chinchilla.labelPlural>Chinchillas</Chinchilla.labelPlural>
  <Chinchilla.lifeStages.0.label>Chinchillajunges</Chinchilla.lifeStages.0.label>
  <Chinchilla.lifeStages.0.labelPlural>Chinchillajunge</Chinchilla.lifeStages.0.labelPlural>
  
  <!-- EN: deer -->
  <Deer.label>Hirsch</Deer.label>
  <!-- EN: doe -->
  <Deer.labelFemale>Hirschkuh</Deer.labelFemale>
  <Deer.labelFemalePlural>Hirschkühe</Deer.labelFemalePlural>
  <!-- EN: buck -->
  <Deer.labelMale>Hirsch</Deer.labelMale>
  <!-- EN: deer -->
  <Deer.labelPlural>Hirsche</Deer.labelPlural>
  <Deer.lifeStages.0.label>Hirschkalb</Deer.lifeStages.0.label>
  <Deer.lifeStages.0.labelPlural>Hirschkälber</Deer.lifeStages.0.labelPlural>
  
  <!-- EN: gazelle -->
  <Gazelle.label>Gazelle</Gazelle.label>
  <Gazelle.labelPlural>Gazellen</Gazelle.labelPlural>
  <Gazelle.lifeStages.0.label>Gazellenjunges</Gazelle.lifeStages.0.label>
  <Gazelle.lifeStages.0.labelPlural>Gazellenjunge</Gazelle.lifeStages.0.labelPlural>
  
  <!-- EN: ibex -->
  <Ibex.label>Steinbock</Ibex.label>
  <!-- EN: ibex doe -->
  <Ibex.labelFemale>Steingeiß</Ibex.labelFemale>
  <Ibex.labelFemalePlural>Steingeißen</Ibex.labelFemalePlural>
  <!-- EN: ibex ram -->
  <Ibex.labelMale>Steinbock</Ibex.labelMale>
  <Ibex.labelMalePlural>Steinböcke</Ibex.labelMalePlural>
  <!-- EN: ibexes -->
  <Ibex.labelPlural>Steinböcke</Ibex.labelPlural>
  <Ibex.lifeStages.0.label>Steinkitz</Ibex.lifeStages.0.label>
  <Ibex.lifeStages.0.labelPlural>Steinkitze</Ibex.lifeStages.0.labelPlural>
  
  <!-- EN: pig -->
  <Pig.label>Schwein</Pig.label>
  <!-- EN: sow -->
  <Pig.labelFemale>Sau</Pig.labelFemale>
  <Pig.labelFemalePlural>Säue</Pig.labelFemalePlural>
  <Pig.labelMale>Eber</Pig.labelMale>
  <Pig.labelMalePlural>Eber</Pig.labelMalePlural>
  <Pig.labelPlural>Schweine</Pig.labelPlural>
  <!-- EN: piglet -->
  <Pig.lifeStages.piglet.label>Ferkel</Pig.lifeStages.piglet.label>
  <Pig.lifeStages.piglet.labelPlural>Ferkel</Pig.lifeStages.piglet.labelPlural>
  
  <!-- EN: wild boar -->
  <WildBoar.label>Wildschwein</WildBoar.label>
  <WildBoar.labelFemale>Bache</WildBoar.labelFemale>
  <WildBoar.labelFemalePlural>Bachen</WildBoar.labelFemalePlural>
  <WildBoar.labelMale>Keiler</WildBoar.labelMale>
  <WildBoar.labelPlural>Keiler</WildBoar.labelPlural>
  <WildBoar.lifeStages.0.label>Frischling</WildBoar.lifeStages.0.label>
  <WildBoar.lifeStages.0.labelPlural>Frischlinge</WildBoar.lifeStages.0.labelPlural>
  
</LanguageData>