<?xml version="1.0" encoding="UTF-8"?>
<LanguageData>
  
  <!-- EN: fat body -->
  <Body_Fat.label>dicker Körper</Body_Fat.label>
  <!-- EN: Carriers can have fat bodies. A person can have more than one body type gene; one body type will be chosen among those that are allowed. -->
  <Body_Fat.description>Träger dieses Gens können einen dicken Körper haben. Eine Person kann mehr als ein Körpertyp-Gen haben; es wird ein zufälliger Körpertyp unter den erlaubten ausgewählt.</Body_Fat.description>
  <!-- EN: fat -->
  <Body_Fat.symbolPack.prefixSymbols.0.symbol>Fett</Body_Fat.symbolPack.prefixSymbols.0.symbol>
  <!-- EN: blub -->
  <Body_Fat.symbolPack.prefixSymbols.1.symbol>Blob</Body_Fat.symbolPack.prefixSymbols.1.symbol>
  <!-- EN: heavy -->
  <Body_Fat.symbolPack.prefixSymbols.2.symbol>Schwer</Body_Fat.symbolPack.prefixSymbols.2.symbol>
  <!-- EN: stomp -->
  <Body_Fat.symbolPack.prefixSymbols.3.symbol>Stomp</Body_Fat.symbolPack.prefixSymbols.3.symbol>
  <!-- EN: flub -->
  <Body_Fat.symbolPack.prefixSymbols.4.symbol>Dick</Body_Fat.symbolPack.prefixSymbols.4.symbol>
  <!-- EN: grease -->
  <Body_Fat.symbolPack.prefixSymbols.5.symbol>Prall</Body_Fat.symbolPack.prefixSymbols.5.symbol>
  <!-- EN: bulk -->
  <Body_Fat.symbolPack.prefixSymbols.6.symbol>Massen</Body_Fat.symbolPack.prefixSymbols.6.symbol>
  <!-- EN: flab -->
  <Body_Fat.symbolPack.prefixSymbols.7.symbol>Speck</Body_Fat.symbolPack.prefixSymbols.7.symbol>
  <!-- EN: lard -->
  <Body_Fat.symbolPack.prefixSymbols.8.symbol>Schmalz</Body_Fat.symbolPack.prefixSymbols.8.symbol>
  <!-- EN: lard -->
  <Body_Fat.symbolPack.suffixSymbols.0.symbol>schmalz</Body_Fat.symbolPack.suffixSymbols.0.symbol>
  <!-- EN: blub -->
  <Body_Fat.symbolPack.suffixSymbols.1.symbol>blob</Body_Fat.symbolPack.suffixSymbols.1.symbol>
  <!-- EN: stomp -->
  <Body_Fat.symbolPack.suffixSymbols.2.symbol>stomp</Body_Fat.symbolPack.suffixSymbols.2.symbol>
  <!-- EN: ball -->
  <Body_Fat.symbolPack.suffixSymbols.3.symbol>kugel</Body_Fat.symbolPack.suffixSymbols.3.symbol>
  
  <!-- EN: hulk body -->
  <Body_Hulk.label>bulliger Körper</Body_Hulk.label>
  <!-- EN: Carriers can have large bodies. A person can have more than one body type gene; one body type will be chosen among those that are allowed. -->
  <Body_Hulk.description>Träger dieses Gens können bullige Körper haben. Eine Person kann mehr als ein Körpertyp-Gen haben; es wird ein zufälliger Körpertyp unter den erlaubten ausgewählt.</Body_Hulk.description>
  <!-- EN: hulk -->
  <Body_Hulk.symbolPack.prefixSymbols.0.symbol>Koloss</Body_Hulk.symbolPack.prefixSymbols.0.symbol>
  <!-- EN: big -->
  <Body_Hulk.symbolPack.prefixSymbols.1.symbol>Groß</Body_Hulk.symbolPack.prefixSymbols.1.symbol>
  <!-- EN: broad -->
  <Body_Hulk.symbolPack.prefixSymbols.2.symbol>Breit</Body_Hulk.symbolPack.prefixSymbols.2.symbol>
  <!-- EN: hunk -->
  <Body_Hulk.symbolPack.prefixSymbols.3.symbol>Brocken</Body_Hulk.symbolPack.prefixSymbols.3.symbol>
  <!-- EN: hulk -->
  <Body_Hulk.symbolPack.suffixSymbols.0.symbol>koloss</Body_Hulk.symbolPack.suffixSymbols.0.symbol>
  <!-- EN: chunk -->
  <Body_Hulk.symbolPack.suffixSymbols.1.symbol>klotz</Body_Hulk.symbolPack.suffixSymbols.1.symbol>
  
  <!-- EN: standard body -->
  <Body_Standard.label>Standardkörper</Body_Standard.label>
  <!-- EN: Carriers can have average-shaped bodies. A person can have more than one body type gene; one body type will be chosen among those that are allowed. -->
  <Body_Standard.description>Träger dieses Gens können normale Körper haben. Eine Person kann mehr als ein Körpertyp-Gen haben; es wird ein zufälliger Körpertyp unter den erlaubten ausgewählt.</Body_Standard.description>
  
  <!-- EN: thin body -->
  <Body_Thin.label>dünner Körper</Body_Thin.label>
  <!-- EN: Carriers can have thin bodies. A person can have more than one body type gene; one body type will be chosen among those that are allowed. -->
  <Body_Thin.description>Träger dieses Gens können dünne Körper haben. Eine Person kann mehr als ein Körpertyp-Gen haben; es wird ein zufälliger Körpertyp unter den erlaubten ausgewählt.</Body_Thin.description>
  <!-- EN: thin -->
  <Body_Thin.symbolPack.prefixSymbols.0.symbol>Dünn</Body_Thin.symbolPack.prefixSymbols.0.symbol>
  <!-- EN: scrawn -->
  <Body_Thin.symbolPack.prefixSymbols.1.symbol>Dürr</Body_Thin.symbolPack.prefixSymbols.1.symbol>
  <!-- EN: lean -->
  <Body_Thin.symbolPack.prefixSymbols.2.symbol>Schlank</Body_Thin.symbolPack.prefixSymbols.2.symbol>
  <!-- EN: slim -->
  <Body_Thin.symbolPack.prefixSymbols.3.symbol>Schmal</Body_Thin.symbolPack.prefixSymbols.3.symbol>
  <!-- EN: pole -->
  <Body_Thin.symbolPack.prefixSymbols.4.symbol>Stangen</Body_Thin.symbolPack.prefixSymbols.4.symbol>
  <!-- EN: wan -->
  <Body_Thin.symbolPack.prefixSymbols.5.symbol>Schwach</Body_Thin.symbolPack.prefixSymbols.5.symbol>
  <!-- EN: bony -->
  <Body_Thin.symbolPack.prefixSymbols.6.symbol>Knochen</Body_Thin.symbolPack.prefixSymbols.6.symbol>
  <!-- EN: lank -->
  <Body_Thin.symbolPack.prefixSymbols.7.symbol>Schmächt</Body_Thin.symbolPack.prefixSymbols.7.symbol>
  <!-- EN: reed -->
  <Body_Thin.symbolPack.prefixSymbols.8.symbol>Halm</Body_Thin.symbolPack.prefixSymbols.8.symbol>
  <!-- EN: slink -->
  <Body_Thin.symbolPack.prefixSymbols.9.symbol>Mager</Body_Thin.symbolPack.prefixSymbols.9.symbol>
  <!-- EN: stilt -->
  <Body_Thin.symbolPack.prefixSymbols.10.symbol>Stelze</Body_Thin.symbolPack.prefixSymbols.10.symbol>
  <!-- EN: twig -->
  <Body_Thin.symbolPack.prefixSymbols.11.symbol>Zweig</Body_Thin.symbolPack.prefixSymbols.11.symbol>
  <!-- EN: stick -->
  <Body_Thin.symbolPack.suffixSymbols.0.symbol>stock</Body_Thin.symbolPack.suffixSymbols.0.symbol>
  <!-- EN: bone -->
  <Body_Thin.symbolPack.suffixSymbols.1.symbol>knochen</Body_Thin.symbolPack.suffixSymbols.1.symbol>
  <!-- EN: pole -->
  <Body_Thin.symbolPack.suffixSymbols.2.symbol>stange</Body_Thin.symbolPack.suffixSymbols.2.symbol>
  <!-- EN: lank -->
  <Body_Thin.symbolPack.suffixSymbols.3.symbol>pinsel</Body_Thin.symbolPack.suffixSymbols.3.symbol>
  <!-- EN: reed -->
  <Body_Thin.symbolPack.suffixSymbols.4.symbol>halm</Body_Thin.symbolPack.suffixSymbols.4.symbol>
  <!-- EN: slink -->
  <Body_Thin.symbolPack.suffixSymbols.5.symbol>mager</Body_Thin.symbolPack.suffixSymbols.5.symbol>
  <!-- EN: stilt -->
  <Body_Thin.symbolPack.suffixSymbols.6.symbol>stelze</Body_Thin.symbolPack.suffixSymbols.6.symbol>
  
  <!-- EN: cat ears -->
  <Ears_Cat.label>Katzenohren</Ears_Cat.label>
  <!-- EN: Carriers of this gene have cat-like ears. -->
  <Ears_Cat.description>Träger dieses Gens haben katzenartige Ohren.</Ears_Cat.description>
  <!-- EN: cat -->
  <Ears_Cat.symbolPack.prefixSymbols.0.symbol>Katzen</Ears_Cat.symbolPack.prefixSymbols.0.symbol>
  <!-- EN: kitty -->
  <Ears_Cat.symbolPack.prefixSymbols.1.symbol>Kit</Ears_Cat.symbolPack.prefixSymbols.1.symbol>
  <!-- EN: kit -->
  <Ears_Cat.symbolPack.prefixSymbols.2.symbol>Miez</Ears_Cat.symbolPack.prefixSymbols.2.symbol>
  <!-- EN: tabby -->
  <Ears_Cat.symbolPack.prefixSymbols.3.symbol>Katzen</Ears_Cat.symbolPack.prefixSymbols.3.symbol>
  <!-- EN: tom -->
  <Ears_Cat.symbolPack.prefixSymbols.4.symbol>Kater</Ears_Cat.symbolPack.prefixSymbols.4.symbol>
  <!-- EN: cat -->
  <Ears_Cat.symbolPack.suffixSymbols.0.symbol>katzen</Ears_Cat.symbolPack.suffixSymbols.0.symbol>
  <!-- EN: kitten -->
  <Ears_Cat.symbolPack.suffixSymbols.1.symbol>kätzchen</Ears_Cat.symbolPack.suffixSymbols.1.symbol>
  <!-- EN: tabby -->
  <Ears_Cat.symbolPack.suffixSymbols.2.symbol>katzen</Ears_Cat.symbolPack.suffixSymbols.2.symbol>
  <!-- EN: tom -->
  <Ears_Cat.symbolPack.suffixSymbols.3.symbol>kater</Ears_Cat.symbolPack.suffixSymbols.3.symbol>
  <!-- EN: ear -->
  <Ears_Cat.symbolPack.suffixSymbols.4.symbol>ohr</Ears_Cat.symbolPack.suffixSymbols.4.symbol>
  
  <!-- EN: floppy ears -->
  <Ears_Floppy.label>Schlappohren</Ears_Floppy.label>
  <!-- EN: Carriers of this gene grow long, floppy hound-like ears. -->
  <Ears_Floppy.description>Träger dieses Gens haben lange, schlaffe, hundeartige Ohren.</Ears_Floppy.description>
  <!-- EN: flop -->
  <Ears_Floppy.symbolPack.prefixSymbols.0.symbol>Schlapp</Ears_Floppy.symbolPack.prefixSymbols.0.symbol>
  <!-- EN: flap -->
  <Ears_Floppy.symbolPack.prefixSymbols.1.symbol>Flatter</Ears_Floppy.symbolPack.prefixSymbols.1.symbol>
  <!-- EN: dog -->
  <Ears_Floppy.symbolPack.prefixSymbols.2.symbol>Hunde</Ears_Floppy.symbolPack.prefixSymbols.2.symbol>
  <!-- EN: droop -->
  <Ears_Floppy.symbolPack.prefixSymbols.3.symbol>Hänge</Ears_Floppy.symbolPack.prefixSymbols.3.symbol>
  <!-- EN: sag -->
  <Ears_Floppy.symbolPack.prefixSymbols.4.symbol>Schlaff</Ears_Floppy.symbolPack.prefixSymbols.4.symbol>
  <!-- EN: hound -->
  <Ears_Floppy.symbolPack.suffixSymbols.0.symbol>köter</Ears_Floppy.symbolPack.suffixSymbols.0.symbol>
  <!-- EN: ear -->
  <Ears_Floppy.symbolPack.suffixSymbols.1.symbol>ohr</Ears_Floppy.symbolPack.suffixSymbols.1.symbol>
  
  <!-- EN: human ears -->
  <Ears_Human.label>menschliche Ohren</Ears_Human.label>
  <!-- EN: Carriers of this gene have regular human ears. -->
  <Ears_Human.description>Träger dieses Gens haben normale menschliche Ohren.</Ears_Human.description>
  
  <!-- EN: pig ears -->
  <Ears_Pig.label>Schweineohren</Ears_Pig.label>
  <!-- EN: Carriers of this gene will grow pointed pig-like ears. -->
  <Ears_Pig.description>Träger dieses Gens haben spitze, schweineähnliche Ohren.</Ears_Pig.description>
  <!-- EN: pig -->
  <Ears_Pig.symbolPack.prefixSymbols.0.symbol>Schweine</Ears_Pig.symbolPack.prefixSymbols.0.symbol>
  <!-- EN: pork -->
  <Ears_Pig.symbolPack.prefixSymbols.1.symbol>Schweine</Ears_Pig.symbolPack.prefixSymbols.1.symbol>
  <!-- EN: pig -->
  <Ears_Pig.symbolPack.suffixSymbols.0.symbol>schwein</Ears_Pig.symbolPack.suffixSymbols.0.symbol>
  <!-- EN: pork -->
  <Ears_Pig.symbolPack.suffixSymbols.1.symbol>pork</Ears_Pig.symbolPack.suffixSymbols.1.symbol>
  <!-- EN: ear -->
  <Ears_Pig.symbolPack.suffixSymbols.2.symbol>ohr</Ears_Pig.symbolPack.suffixSymbols.2.symbol>
  
  <!-- EN: pointed ears -->
  <Ears_Pointed.label>spitze Ohren</Ears_Pointed.label>
  <!-- EN: Carriers of this gene have pointed ears. -->
  <Ears_Pointed.description>Träger dieses Gens haben spitze Ohren.</Ears_Pointed.description>
  <!-- EN: point -->
  <Ears_Pointed.symbolPack.prefixSymbols.0.symbol>Spitz</Ears_Pointed.symbolPack.prefixSymbols.0.symbol>
  <!-- EN: sharp -->
  <Ears_Pointed.symbolPack.prefixSymbols.1.symbol>Spitz</Ears_Pointed.symbolPack.prefixSymbols.1.symbol>
  <!-- EN: ear -->
  <Ears_Pointed.symbolPack.suffixSymbols.0.symbol>ohr</Ears_Pointed.symbolPack.suffixSymbols.0.symbol>
  <!-- EN: point -->
  <Ears_Pointed.symbolPack.suffixSymbols.1.symbol>spitz</Ears_Pointed.symbolPack.suffixSymbols.1.symbol>
  
  <!-- EN: elongated fingers -->
  <ElongatedFingers.label>lange Finger</ElongatedFingers.label>
  <!-- EN: Long, delicate fingers improve the carrier's manipulation capacity. This aids with many tasks, especially crafting and construction. -->
  <ElongatedFingers.description>Träger dieses Gens haben lange, zarte Finger, was bei vielen Tätigkeiten, vor allem beim Handwerk und Bauen, hilfreich ist.</ElongatedFingers.description>
  <!-- EN: long -->
  <ElongatedFingers.symbolPack.prefixSymbols.0.symbol>Lang</ElongatedFingers.symbolPack.prefixSymbols.0.symbol>
  <!-- EN: elon -->
  <ElongatedFingers.symbolPack.prefixSymbols.1.symbol>Lang</ElongatedFingers.symbolPack.prefixSymbols.1.symbol>
  <!-- EN: pencil -->
  <ElongatedFingers.symbolPack.prefixSymbols.2.symbol>Stift</ElongatedFingers.symbolPack.prefixSymbols.2.symbol>
  <!-- EN: finger -->
  <ElongatedFingers.symbolPack.suffixSymbols.0.symbol>finger</ElongatedFingers.symbolPack.suffixSymbols.0.symbol>
  <!-- EN: dactyl -->
  <ElongatedFingers.symbolPack.suffixSymbols.1.symbol>daktylus</ElongatedFingers.symbolPack.suffixSymbols.1.symbol>
  <!-- EN: digit -->
  <ElongatedFingers.symbolPack.suffixSymbols.2.symbol>griffel</ElongatedFingers.symbolPack.suffixSymbols.2.symbol>
  
  <!-- EN: human hands -->
  <Hands_Human.label>menschliche Hände</Hands_Human.label>
  <!-- EN: Carriers of this gene have regular human hands. -->
  <Hands_Human.description>Träger dieses Gens haben normale menschliche Hände.</Hands_Human.description>
  
  <!-- EN: trotter hands -->
  <Hands_Pig.label>schweinefüßige Hände</Hands_Pig.label>
  <!-- EN: Carriers of this gene have hands that partially resemble pig trotters. This reduces their ability to manipulate objects. -->
  <Hands_Pig.description>Träger dieses Gens haben Hände, die teilweise wie Schweinefüße aussehen. Dies schränkt ihre Fähigkeit ein, mit Gegenständen zu hantieren.</Hands_Pig.description>
  <!-- EN: trot -->
  <Hands_Pig.symbolPack.prefixSymbols.0.symbol>Trab</Hands_Pig.symbolPack.prefixSymbols.0.symbol>
  <!-- EN: pig -->
  <Hands_Pig.symbolPack.prefixSymbols.1.symbol>Schwein</Hands_Pig.symbolPack.prefixSymbols.1.symbol>
  <!-- EN: pork -->
  <Hands_Pig.symbolPack.prefixSymbols.2.symbol>Pork</Hands_Pig.symbolPack.prefixSymbols.2.symbol>
  <!-- EN: boar -->
  <Hands_Pig.symbolPack.prefixSymbols.3.symbol>Eber</Hands_Pig.symbolPack.prefixSymbols.3.symbol>
  <!-- EN: hog -->
  <Hands_Pig.symbolPack.prefixSymbols.4.symbol>Schwein</Hands_Pig.symbolPack.prefixSymbols.4.symbol>
  <!-- EN: trot -->
  <Hands_Pig.symbolPack.suffixSymbols.0.symbol>trab</Hands_Pig.symbolPack.suffixSymbols.0.symbol>
  <!-- EN: pig -->
  <Hands_Pig.symbolPack.suffixSymbols.1.symbol>schwein</Hands_Pig.symbolPack.suffixSymbols.1.symbol>
  <!-- EN: swine -->
  <Hands_Pig.symbolPack.suffixSymbols.2.symbol>schwein</Hands_Pig.symbolPack.suffixSymbols.2.symbol>
  <!-- EN: boar -->
  <Hands_Pig.symbolPack.suffixSymbols.3.symbol>eber</Hands_Pig.symbolPack.suffixSymbols.3.symbol>
  <!-- EN: hog -->
  <Hands_Pig.symbolPack.suffixSymbols.4.symbol>schwein</Hands_Pig.symbolPack.suffixSymbols.4.symbol>
  <!-- EN: trotter -->
  <Hands_Pig.symbolPack.wholeNameSymbols.0.symbol>Fuß</Hands_Pig.symbolPack.wholeNameSymbols.0.symbol>
  
  <!-- EN: gaunt head -->
  <Head_Gaunt.label>magerer Kopf</Head_Gaunt.label>
  <!-- EN: Carriers of this gene have a pinched, gaunt appearance in their face and head. -->
  <Head_Gaunt.description>Träger dieses Gens haben ein eingefallenes, mageres Aussehen im Gesicht und am Kopf.</Head_Gaunt.description>
  <!-- EN: gaunt -->
  <Head_Gaunt.symbolPack.prefixSymbols.0.symbol>Mager</Head_Gaunt.symbolPack.prefixSymbols.0.symbol>
  <!-- EN: skull -->
  <Head_Gaunt.symbolPack.prefixSymbols.1.symbol>Schädel</Head_Gaunt.symbolPack.prefixSymbols.1.symbol>
  <!-- EN: dead -->
  <Head_Gaunt.symbolPack.prefixSymbols.2.symbol>Tod</Head_Gaunt.symbolPack.prefixSymbols.2.symbol>
  <!-- EN: bone -->
  <Head_Gaunt.symbolPack.prefixSymbols.3.symbol>Knochen</Head_Gaunt.symbolPack.prefixSymbols.3.symbol>
  
  <!-- EN: center-horn -->
  <Headbone_CenterHorn.label>Einhorn</Headbone_CenterHorn.label>
  <!-- EN: Carriers of this gene grow a single horn protruding from the center of the forehead. -->
  <Headbone_CenterHorn.description>Träger dieses Gens haben ein einzelnes Horn, das aus der Mitte der Stirn herausragt.</Headbone_CenterHorn.description>
  <!-- EN: rhino -->
  <Headbone_CenterHorn.symbolPack.prefixSymbols.0.symbol>Rhino</Headbone_CenterHorn.symbolPack.prefixSymbols.0.symbol>
  <!-- EN: horn -->
  <Headbone_CenterHorn.symbolPack.prefixSymbols.1.symbol>Horn</Headbone_CenterHorn.symbolPack.prefixSymbols.1.symbol>
  <!-- EN: knob -->
  <Headbone_CenterHorn.symbolPack.prefixSymbols.2.symbol>Höcker</Headbone_CenterHorn.symbolPack.prefixSymbols.2.symbol>
  <!-- EN: spike -->
  <Headbone_CenterHorn.symbolPack.prefixSymbols.3.symbol>Stachel</Headbone_CenterHorn.symbolPack.prefixSymbols.3.symbol>
  <!-- EN: horn -->
  <Headbone_CenterHorn.symbolPack.suffixSymbols.0.symbol>horn</Headbone_CenterHorn.symbolPack.suffixSymbols.0.symbol>
  <!-- EN: spike -->
  <Headbone_CenterHorn.symbolPack.suffixSymbols.1.symbol>stachel</Headbone_CenterHorn.symbolPack.suffixSymbols.1.symbol>
  
  <!-- EN: human headbone -->
  <Headbone_Human.label>menschlicher Schädel</Headbone_Human.label>
  <!-- EN: Carriers of this gene have regular human skulls. -->
  <Headbone_Human.description>Träger dieses Gens haben einen normalen menschlichen Schädel.</Headbone_Human.description>
  
  <!-- EN: mini-horns -->
  <Headbone_MiniHorns.label>Teufelshörner</Headbone_MiniHorns.label>
  <!-- EN: Carriers of this gene grow two small horns protruding from the forehead. -->
  <Headbone_MiniHorns.description>Träger dieses Gens haben zwei kleine Hörner, die aus der Stirn herausragen.</Headbone_MiniHorns.description>
  <!-- EN: horn -->
  <Headbone_MiniHorns.symbolPack.prefixSymbols.0.symbol>Horn</Headbone_MiniHorns.symbolPack.prefixSymbols.0.symbol>
  <!-- EN: knob -->
  <Headbone_MiniHorns.symbolPack.prefixSymbols.1.symbol>Höcker</Headbone_MiniHorns.symbolPack.prefixSymbols.1.symbol>
  <!-- EN: spike -->
  <Headbone_MiniHorns.symbolPack.prefixSymbols.2.symbol>Stachel</Headbone_MiniHorns.symbolPack.prefixSymbols.2.symbol>
  <!-- EN: devil -->
  <Headbone_MiniHorns.symbolPack.prefixSymbols.3.symbol>Teufel</Headbone_MiniHorns.symbolPack.prefixSymbols.3.symbol>
  <!-- EN: demon -->
  <Headbone_MiniHorns.symbolPack.prefixSymbols.4.symbol>Dämon</Headbone_MiniHorns.symbolPack.prefixSymbols.4.symbol>
  <!-- EN: luci -->
  <Headbone_MiniHorns.symbolPack.prefixSymbols.5.symbol>Luzi</Headbone_MiniHorns.symbolPack.prefixSymbols.5.symbol>
  <!-- EN: beelze -->
  <Headbone_MiniHorns.symbolPack.prefixSymbols.6.symbol>Beelze</Headbone_MiniHorns.symbolPack.prefixSymbols.6.symbol>
  <!-- EN: hell -->
  <Headbone_MiniHorns.symbolPack.prefixSymbols.7.symbol>Hölle</Headbone_MiniHorns.symbolPack.prefixSymbols.7.symbol>
  <!-- EN: horn -->
  <Headbone_MiniHorns.symbolPack.suffixSymbols.0.symbol>horn</Headbone_MiniHorns.symbolPack.suffixSymbols.0.symbol>
  <!-- EN: spike -->
  <Headbone_MiniHorns.symbolPack.suffixSymbols.1.symbol>stachel</Headbone_MiniHorns.symbolPack.suffixSymbols.1.symbol>
  <!-- EN: vil -->
  <Headbone_MiniHorns.symbolPack.suffixSymbols.2.symbol>fel</Headbone_MiniHorns.symbolPack.suffixSymbols.2.symbol>
  
  <!-- EN: human jaw -->
  <Jaw_Baseline.label>menschlicher Kiefer</Jaw_Baseline.label>
  <!-- EN: Carriers of this gene have regularly-shaped jaws. -->
  <Jaw_Baseline.description>Träger dieses Gens haben einen normal geformten Kiefer.</Jaw_Baseline.description>
  
  <!-- EN: heavy jaw -->
  <Jaw_Heavy.label>kräftiger Kiefer</Jaw_Heavy.label>
  <!-- EN: Carriers of this gene have large jaws. -->
  <Jaw_Heavy.description>Träger dieses Gens haben einen kräftigen Kiefer.</Jaw_Heavy.description>
  <!-- EN: grunt -->
  <Jaw_Heavy.symbolPack.prefixSymbols.0.symbol>Groß</Jaw_Heavy.symbolPack.prefixSymbols.0.symbol>
  <!-- EN: jaw -->
  <Jaw_Heavy.symbolPack.prefixSymbols.1.symbol>Kiefer</Jaw_Heavy.symbolPack.prefixSymbols.1.symbol>
  <!-- EN: lug -->
  <Jaw_Heavy.symbolPack.prefixSymbols.2.symbol>Kraft</Jaw_Heavy.symbolPack.prefixSymbols.2.symbol>
  <!-- EN: grunt -->
  <Jaw_Heavy.symbolPack.suffixSymbols.0.symbol>groß</Jaw_Heavy.symbolPack.suffixSymbols.0.symbol>
  <!-- EN: jaw -->
  <Jaw_Heavy.symbolPack.suffixSymbols.1.symbol>kiefer</Jaw_Heavy.symbolPack.suffixSymbols.1.symbol>
  <!-- EN: lug -->
  <Jaw_Heavy.symbolPack.suffixSymbols.2.symbol>kauleiste</Jaw_Heavy.symbolPack.suffixSymbols.2.symbol>
  <!-- EN: thal -->
  <Jaw_Heavy.symbolPack.suffixSymbols.3.symbol>kiefer</Jaw_Heavy.symbolPack.suffixSymbols.3.symbol>
  
  <!-- EN: human nose -->
  <Nose_Human.label>menschliche Nase</Nose_Human.label>
  <!-- EN: Carriers of this gene have regular human noses. -->
  <Nose_Human.description>Träger dieses Gens haben normale menschliche Nasen.</Nose_Human.description>
  
  <!-- EN: pig nose -->
  <Nose_Pig.label>Schweinenase</Nose_Pig.label>
  <!-- EN: Carriers of this gene have pig-like snouts. -->
  <Nose_Pig.description>Träger dieses Gens haben eine schweineartige Nase.</Nose_Pig.description>
  <!-- EN: pig -->
  <Nose_Pig.symbolPack.prefixSymbols.0.symbol>Schwein</Nose_Pig.symbolPack.prefixSymbols.0.symbol>
  <!-- EN: pork -->
  <Nose_Pig.symbolPack.prefixSymbols.1.symbol>Pork</Nose_Pig.symbolPack.prefixSymbols.1.symbol>
  <!-- EN: snout -->
  <Nose_Pig.symbolPack.prefixSymbols.2.symbol>Schnauz</Nose_Pig.symbolPack.prefixSymbols.2.symbol>
  <!-- EN: boar -->
  <Nose_Pig.symbolPack.prefixSymbols.3.symbol>Eber</Nose_Pig.symbolPack.prefixSymbols.3.symbol>
  <!-- EN: hog -->
  <Nose_Pig.symbolPack.prefixSymbols.4.symbol>Schwein</Nose_Pig.symbolPack.prefixSymbols.4.symbol>
  <!-- EN: pig -->
  <Nose_Pig.symbolPack.suffixSymbols.0.symbol>schwein</Nose_Pig.symbolPack.suffixSymbols.0.symbol>
  <!-- EN: snout -->
  <Nose_Pig.symbolPack.suffixSymbols.1.symbol>schnauze</Nose_Pig.symbolPack.suffixSymbols.1.symbol>
  <!-- EN: swine -->
  <Nose_Pig.symbolPack.suffixSymbols.2.symbol>schwein</Nose_Pig.symbolPack.suffixSymbols.2.symbol>
  <!-- EN: boar -->
  <Nose_Pig.symbolPack.suffixSymbols.3.symbol>eber</Nose_Pig.symbolPack.suffixSymbols.3.symbol>
  <!-- EN: hog -->
  <Nose_Pig.symbolPack.suffixSymbols.4.symbol>schwein</Nose_Pig.symbolPack.suffixSymbols.4.symbol>
  <!-- EN: nose -->
  <Nose_Pig.symbolPack.suffixSymbols.5.symbol>nase</Nose_Pig.symbolPack.suffixSymbols.5.symbol>
  
  <!-- EN: human voice -->
  <Voice_Human.label>menschliche Stimme</Voice_Human.label>
  <!-- EN: Carriers of this gene have regular human vocal cords. -->
  <Voice_Human.description>Träger dieses Gens haben normale menschliche Stimmbänder.</Voice_Human.description>
  
  <!-- EN: pig voice -->
  <VoicePig.label>quickende Stimme</VoicePig.label>
  <!-- EN: Carriers have a squealing voice like that of a pig. -->
  <VoicePig.description>Träger dieses Gens haben eine quiekende Stimme wie ein Schwein.</VoicePig.description>
  <!-- EN: squeal -->
  <VoicePig.symbolPack.prefixSymbols.0.symbol>Quiek</VoicePig.symbolPack.prefixSymbols.0.symbol>
  <!-- EN: oink -->
  <VoicePig.symbolPack.prefixSymbols.1.symbol>Grunz</VoicePig.symbolPack.prefixSymbols.1.symbol>
  <!-- EN: snuffle -->
  <VoicePig.symbolPack.prefixSymbols.2.symbol>Schnüffel</VoicePig.symbolPack.prefixSymbols.2.symbol>
  <!-- EN: snort -->
  <VoicePig.symbolPack.prefixSymbols.3.symbol>Schnaub</VoicePig.symbolPack.prefixSymbols.3.symbol>
  <!-- EN: oinker -->
  <VoicePig.symbolPack.suffixSymbols.0.symbol>grunzer</VoicePig.symbolPack.suffixSymbols.0.symbol>
  <!-- EN: hog -->
  <VoicePig.symbolPack.suffixSymbols.1.symbol>schwein</VoicePig.symbolPack.suffixSymbols.1.symbol>
  <!-- EN: pig -->
  <VoicePig.symbolPack.suffixSymbols.2.symbol>schwein</VoicePig.symbolPack.suffixSymbols.2.symbol>
  <!-- EN: snorter -->
  <VoicePig.symbolPack.suffixSymbols.3.symbol>schnauber</VoicePig.symbolPack.suffixSymbols.3.symbol>
  <!-- EN: squealer -->
  <VoicePig.symbolPack.wholeNameSymbols.0.symbol>Quieker</VoicePig.symbolPack.wholeNameSymbols.0.symbol>
  <!-- EN: oinker -->
  <VoicePig.symbolPack.wholeNameSymbols.1.symbol>Grunzer</VoicePig.symbolPack.wholeNameSymbols.1.symbol>
  <!-- EN: snorter -->
  <VoicePig.symbolPack.wholeNameSymbols.2.symbol>Schnauber</VoicePig.symbolPack.wholeNameSymbols.2.symbol>
  
  <!-- EN: roar voice -->
  <VoiceRoar.label>brüllende Stimme</VoiceRoar.label>
  <!-- EN: Carriers have an animal-like roaring voice. -->
  <VoiceRoar.description>Träger dieses Gens haben eine tierähnliche brüllende Stimme.</VoiceRoar.description>
  <!-- EN: roar -->
  <VoiceRoar.symbolPack.prefixSymbols.0.symbol>Brüll</VoiceRoar.symbolPack.prefixSymbols.0.symbol>
  <!-- EN: growl -->
  <VoiceRoar.symbolPack.prefixSymbols.1.symbol>Knurr</VoiceRoar.symbolPack.prefixSymbols.1.symbol>
  <!-- EN: snarl -->
  <VoiceRoar.symbolPack.prefixSymbols.2.symbol>Fauch</VoiceRoar.symbolPack.prefixSymbols.2.symbol>
  <!-- EN: roar -->
  <VoiceRoar.symbolPack.suffixSymbols.0.symbol>gebrüll</VoiceRoar.symbolPack.suffixSymbols.0.symbol>
  <!-- EN: snarl -->
  <VoiceRoar.symbolPack.suffixSymbols.1.symbol>gefauche</VoiceRoar.symbolPack.suffixSymbols.1.symbol>
  <!-- EN: growl -->
  <VoiceRoar.symbolPack.suffixSymbols.2.symbol>geknurre</VoiceRoar.symbolPack.suffixSymbols.2.symbol>
  <!-- EN: roarer -->
  <VoiceRoar.symbolPack.wholeNameSymbols.0.symbol>Brüller</VoiceRoar.symbolPack.wholeNameSymbols.0.symbol>
  <!-- EN: growler -->
  <VoiceRoar.symbolPack.wholeNameSymbols.1.symbol>Knurrer</VoiceRoar.symbolPack.wholeNameSymbols.1.symbol>
  <!-- EN: snarler -->
  <VoiceRoar.symbolPack.wholeNameSymbols.2.symbol>Faucher</VoiceRoar.symbolPack.wholeNameSymbols.2.symbol>
  <!-- EN: bellower -->
  <VoiceRoar.symbolPack.wholeNameSymbols.3.symbol>Gröler</VoiceRoar.symbolPack.wholeNameSymbols.3.symbol>
  
</LanguageData>