<?xml version="1.0" encoding="utf-8"?>
<LanguageData>
  
  <!-- EN: release -->
  <BasicReleasePrisoner.verb>Gefangenen freilassen</BasicReleasePrisoner.verb>
  <!-- EN: releasing -->
  <BasicReleasePrisoner.gerund>lass Gefangenen frei</BasicReleasePrisoner.gerund>
  <!-- EN: release prisoners -->
  <BasicReleasePrisoner.label>Gefangene freilassen</BasicReleasePrisoner.label>
  
  <!-- EN: build roof -->
  <BuildRoofs.verb>Dächer errichten</BuildRoofs.verb>
  <!-- EN: building roof -->
  <BuildRoofs.gerund>errichte Dächer</BuildRoofs.gerund>
  <!-- EN: build roofs -->
  <BuildRoofs.label>Dächer errichten</BuildRoofs.label>
  
  <!-- EN: chat with -->
  <ChatWithPrisoner.verb>reden</ChatWithPrisoner.verb>
  <!-- EN: chatting with -->
  <ChatWithPrisoner.gerund>rede mit</ChatWithPrisoner.gerund>
  <!-- EN: chat with prisoners -->
  <ChatWithPrisoner.label>Mit Gefangenen reden</ChatWithPrisoner.label>
  
  <!-- EN: clear snow -->
  <CleanClearSnow.verb>kehren</CleanClearSnow.verb>
  <!-- EN: clearing snow -->
  <CleanClearSnow.gerund>kehre</CleanClearSnow.gerund>
  <!-- EN: clear snow -->
  <CleanClearSnow.label>Schnee kehren</CleanClearSnow.label>
  
  <!-- EN: clean -->
  <CleanFilth.verb>reinigen</CleanFilth.verb>
  <!-- EN: cleaning -->
  <CleanFilth.gerund>reinige</CleanFilth.gerund>
  <!-- EN: clean filth -->
  <CleanFilth.label>Boden reinigen</CleanFilth.label>
  
  <!-- EN: work on -->
  <ConstructDeliverResourcesToBlueprints.verb>arbeiten</ConstructDeliverResourcesToBlueprints.verb>
  <!-- EN: working on -->
  <ConstructDeliverResourcesToBlueprints.gerund>arbeite</ConstructDeliverResourcesToBlueprints.gerund>
  <!-- EN: deliver resources to blueprints -->
  <ConstructDeliverResourcesToBlueprints.label>Rohstoffe zum Bauplan bringen</ConstructDeliverResourcesToBlueprints.label>
  
  <!-- EN: work on -->
  <ConstructDeliverResourcesToFrames.verb>arbeiten</ConstructDeliverResourcesToFrames.verb>
  <!-- EN: working on -->
  <ConstructDeliverResourcesToFrames.gerund>arbeite</ConstructDeliverResourcesToFrames.gerund>
  <!-- EN: deliver resources to frames -->
  <ConstructDeliverResourcesToFrames.label>Rohstoffe zum Gerüst bringen</ConstructDeliverResourcesToFrames.label>
  
  <!-- EN: construct -->
  <ConstructFinishFrames.verb>bauen</ConstructFinishFrames.verb>
  <!-- EN: constructing -->
  <ConstructFinishFrames.gerund>baue</ConstructFinishFrames.gerund>
  <!-- EN: construct placed frames -->
  <ConstructFinishFrames.label>Gerüst ausbauen</ConstructFinishFrames.label>
  
  <!-- EN: remove floor -->
  <ConstructRemoveFloors.verb>Boden entfernen</ConstructRemoveFloors.verb>
  <!-- EN: removing floor -->
  <ConstructRemoveFloors.gerund>entferne Boden</ConstructRemoveFloors.gerund>
  <!-- EN: remove floors -->
  <ConstructRemoveFloors.label>Böden entfernen</ConstructRemoveFloors.label>
  
  <!-- EN: smooth -->
  <ConstructSmoothFloors.verb>glätten</ConstructSmoothFloors.verb>
  <!-- EN: smoothing -->
  <ConstructSmoothFloors.gerund>glätte</ConstructSmoothFloors.gerund>
  <!-- EN: smooth floors -->
  <ConstructSmoothFloors.label>Böden glätten</ConstructSmoothFloors.label>
  
  <!-- EN: smooth -->
  <ConstructSmoothWalls.verb>glätten</ConstructSmoothWalls.verb>
  <!-- EN: smoothing -->
  <ConstructSmoothWalls.gerund>glätte</ConstructSmoothWalls.gerund>
  <!-- EN: smooth walls -->
  <ConstructSmoothWalls.label>Wände glätten</ConstructSmoothWalls.label>
  
  <!-- EN: fill -->
  <CookFillHopper.verb>auffüllen</CookFillHopper.verb>
  <!-- EN: filling -->
  <CookFillHopper.gerund>fülle</CookFillHopper.gerund>
  <!-- EN: fill food hoppers -->
  <CookFillHopper.label>Trichter auffüllen</CookFillHopper.label>
  
  <!-- EN: deconstruct -->
  <Deconstruct.verb>abreißen</Deconstruct.verb>
  <!-- EN: deconstructing -->
  <Deconstruct.gerund>reiße ab</Deconstruct.gerund>
  <!-- EN: deconstruct structures -->
  <Deconstruct.label>Strukturen abreißen</Deconstruct.label>
  
  <!-- EN: deliver food for -->
  <DeliverFoodToPrisoner.verb>bringen</DeliverFoodToPrisoner.verb>
  <!-- EN: delivering food for -->
  <DeliverFoodToPrisoner.gerund>bringe Essen zu</DeliverFoodToPrisoner.gerund>
  <!-- EN: deliver food to prisoners -->
  <DeliverFoodToPrisoner.label>Essen zu Gefangenen bringen</DeliverFoodToPrisoner.label>
  
  <!-- EN: deliver to -->
  <DeliverResourcesToBlueprints.verb>liefern zu</DeliverResourcesToBlueprints.verb>
  <!-- EN: delivering to -->
  <DeliverResourcesToBlueprints.gerund>liefere zu</DeliverResourcesToBlueprints.gerund>
  <!-- EN: deliver resources to blueprints -->
  <DeliverResourcesToBlueprints.label>Transportiere Dinge zu Blaupausen</DeliverResourcesToBlueprints.label>
  
  <!-- EN: deliver to -->
  <DeliverResourcesToFrames.verb>liefern zu</DeliverResourcesToFrames.verb>
  <!-- EN: delivering to -->
  <DeliverResourcesToFrames.gerund>liefere zu</DeliverResourcesToFrames.gerund>
  <!-- EN: deliver resources to frames -->
  <DeliverResourcesToFrames.label>Transportiere Dinge zu Gerüste</DeliverResourcesToFrames.label>
  
  <!-- EN: brew -->
  <DoBillsBrew.verb>brauen</DoBillsBrew.verb>
  <!-- EN: brewing at -->
  <DoBillsBrew.gerund>braue</DoBillsBrew.gerund>
  <!-- EN: brew liquors -->
  <DoBillsBrew.label>Alkohol brauen</DoBillsBrew.label>
  
  <!-- EN: butcher -->
  <DoBillsButcherFlesh.verb>schlachten</DoBillsButcherFlesh.verb>
  <!-- EN: butchering at -->
  <DoBillsButcherFlesh.gerund>schlachte</DoBillsButcherFlesh.gerund>
  <!-- EN: butcher creatures -->
  <DoBillsButcherFlesh.label>Kreatur schlachten</DoBillsButcherFlesh.label>
  
  <!-- EN: cook -->
  <DoBillsCook.verb>kochen</DoBillsCook.verb>
  <!-- EN: cooking at -->
  <DoBillsCook.gerund>koche</DoBillsCook.gerund>
  <!-- EN: cook meals at stove -->
  <DoBillsCook.label>Mahlzeit am Herd kochen</DoBillsCook.label>
  
  <!-- EN: cook -->
  <DoBillsCookCampfire.verb>kochen</DoBillsCookCampfire.verb>
  <!-- EN: cooking at -->
  <DoBillsCookCampfire.gerund>koche</DoBillsCookCampfire.gerund>
  <!-- EN: cook meals at campfire -->
  <DoBillsCookCampfire.label>Mahlzeit am Lagerfeuer kochen</DoBillsCookCampfire.label>
  
  <!-- EN: cremate -->
  <DoBillsCremate.verb>einäschern</DoBillsCremate.verb>
  <!-- EN: cremating at -->
  <DoBillsCremate.gerund>einäschern</DoBillsCremate.gerund>
  <!-- EN: do cremation bills -->
  <DoBillsCremate.label>Leichen einäschern</DoBillsCremate.label>
  
  <!-- EN: fabricating things -->
  <DoBillsFabricationBench.verb>Dinge produzieren</DoBillsFabricationBench.verb>
  <!-- EN: fabricating things at -->
  <DoBillsFabricationBench.gerund>produziere Dinge</DoBillsFabricationBench.gerund>
  <!-- EN: fabricate things -->
  <DoBillsFabricationBench.label>Dinge herstellen</DoBillsFabricationBench.label>
  
  <!-- EN: work at -->
  <DoBillsHaulCampfire.verb>arbeiten</DoBillsHaulCampfire.verb>
  <!-- EN: working at -->
  <DoBillsHaulCampfire.gerund>arbeite an</DoBillsHaulCampfire.gerund>
  <!-- EN: do bills at campfire -->
  <DoBillsHaulCampfire.label>Erledige Aufgaben am Lagerfeuer</DoBillsHaulCampfire.label>
  
  <!-- EN: work -->
  <DoBillsMachiningTable.verb>arbeiten</DoBillsMachiningTable.verb>
  <!-- EN: working at -->
  <DoBillsMachiningTable.gerund>arbeite</DoBillsMachiningTable.gerund>
  <!-- EN: make things at machining table -->
  <DoBillsMachiningTable.label>an der Mechanik Werkbank arbeiten</DoBillsMachiningTable.label>
  
  <!-- EN: tailor -->
  <DoBillsMakeApparel.verb>schneidern</DoBillsMakeApparel.verb>
  <!-- EN: tailoring at -->
  <DoBillsMakeApparel.gerund>schneidere</DoBillsMakeApparel.gerund>
  <!-- EN: make apparel -->
  <DoBillsMakeApparel.label>Kleidung schneidern</DoBillsMakeApparel.label>
  
  <!-- EN: smith -->
  <DoBillsMakeWeapons.verb>produzieren</DoBillsMakeWeapons.verb>
  <!-- EN: smithing at -->
  <DoBillsMakeWeapons.gerund>produziere</DoBillsMakeWeapons.gerund>
  <!-- EN: make weapons -->
  <DoBillsMakeWeapons.label>Waffe herstellen</DoBillsMakeWeapons.label>
  
  <!-- EN: operate on -->
  <DoBillsMedicalAnimalOperation.verb>operieren auf</DoBillsMedicalAnimalOperation.verb>
  <!-- EN: operating on -->
  <DoBillsMedicalAnimalOperation.gerund>operiere auf</DoBillsMedicalAnimalOperation.gerund>
  <!-- EN: operate on animals -->
  <DoBillsMedicalAnimalOperation.label>Tiere operieren</DoBillsMedicalAnimalOperation.label>
  
  <!-- EN: operate on -->
  <DoBillsMedicalHumanOperation.verb>operieren auf</DoBillsMedicalHumanOperation.verb>
  <!-- EN: operating on -->
  <DoBillsMedicalHumanOperation.gerund>operiere auf</DoBillsMedicalHumanOperation.gerund>
  <!-- EN: operate on humanlikes -->
  <DoBillsMedicalHumanOperation.label>Patienten operieren</DoBillsMedicalHumanOperation.label>
  
  <!-- EN: produce drugs -->
  <DoBillsProduceDrugs.verb>Drogen synthetisieren auf</DoBillsProduceDrugs.verb>
  <!-- EN: producing drugs at -->
  <DoBillsProduceDrugs.gerund>Synthetisiere Drogen auf</DoBillsProduceDrugs.gerund>
  <!-- EN: synthesize drugs -->
  <DoBillsProduceDrugs.label>Synthetisiere Drogen</DoBillsProduceDrugs.label>
  
  <!-- EN: refine chemicals -->
  <DoBillsRefinery.verb>Chemikalien verarbeiten</DoBillsRefinery.verb>
  <!-- EN: refining chemicals at -->
  <DoBillsRefinery.gerund>verarbeite Chemikalien auf</DoBillsRefinery.gerund>
  <!-- EN: work at refinery -->
  <DoBillsRefinery.label>Mit Raffinerie arbeiten</DoBillsRefinery.label>
  
  <!-- EN: sculpt -->
  <DoBillsSculpt.verb>am Kunstwerk arbeiten</DoBillsSculpt.verb>
  <!-- EN: sculpting at -->
  <DoBillsSculpt.gerund>arbeite am Kunstwerk</DoBillsSculpt.gerund>
  <!-- EN: make sculptures -->
  <DoBillsSculpt.label>Kunstwerk erstellen</DoBillsSculpt.label>
  
  <!-- EN: refine -->
  <DoBillsSmelter.verb>veredeln</DoBillsSmelter.verb>
  <!-- EN: refining at -->
  <DoBillsSmelter.gerund>veredle</DoBillsSmelter.gerund>
  <!-- EN: smelt items -->
  <DoBillsSmelter.label>schmelze Dinge ein</DoBillsSmelter.label>
  
  <!-- EN: stonecut -->
  <DoBillsStonecut.verb>Steine bearbeiten auf</DoBillsStonecut.verb>
  <!-- EN: cutting stone blocks at -->
  <DoBillsStonecut.gerund>bearbeite Steine auf</DoBillsStonecut.gerund>
  <!-- EN: make stone blocks -->
  <DoBillsStonecut.label>Steine bearbeiten</DoBillsStonecut.label>
  
  <!-- EN: craft -->
  <DoBillsUseCraftingSpot.verb>fertigen</DoBillsUseCraftingSpot.verb>
  <!-- EN: crafting at -->
  <DoBillsUseCraftingSpot.gerund>fertige</DoBillsUseCraftingSpot.gerund>
  <!-- EN: make things at crafting spot -->
  <DoBillsUseCraftingSpot.label>Dinge am Arbeitsplatz fertigen</DoBillsUseCraftingSpot.label>
  
  <!-- EN: feed -->
  <DoctorFeedAnimals.verb>Tier füttern</DoctorFeedAnimals.verb>
  <!-- EN: feeding -->
  <DoctorFeedAnimals.gerund>füttere</DoctorFeedAnimals.gerund>
  <!-- EN: feed animals -->
  <DoctorFeedAnimals.label>Tiere füttern</DoctorFeedAnimals.label>
  
  <!-- EN: feed -->
  <DoctorFeedHumanlikes.verb>Patient füttern</DoctorFeedHumanlikes.verb>
  <!-- EN: feeding -->
  <DoctorFeedHumanlikes.gerund>füttere</DoctorFeedHumanlikes.gerund>
  <!-- EN: feed patients -->
  <DoctorFeedHumanlikes.label>Patienten füttern</DoctorFeedHumanlikes.label>
  
  <!-- EN: rescue -->
  <DoctorRescue.verb>retten</DoctorRescue.verb>
  <!-- EN: rescuing -->
  <DoctorRescue.gerund>rette</DoctorRescue.gerund>
  <!-- EN: rescue downed allies to bed -->
  <DoctorRescue.label>Bewusstlose Kolonisten ins Bett transportieren</DoctorRescue.label>
  
  <!-- EN: tend to -->
  <DoctorTendEmergency.verb>behandeln</DoctorTendEmergency.verb>
  <!-- EN: tending to -->
  <DoctorTendEmergency.gerund>behandle</DoctorTendEmergency.gerund>
  <!-- EN: tend to patients with urgent needs -->
  <DoctorTendEmergency.label>Patienten mit dringenden Bedürfnissen behandeln</DoctorTendEmergency.label>
  
  <!-- EN: tend to -->
  <DoctorTendToAnimals.verb>Tier behandeln</DoctorTendToAnimals.verb>
  <!-- EN: tending to -->
  <DoctorTendToAnimals.gerund>behandle</DoctorTendToAnimals.gerund>
  <!-- EN: tend to animals -->
  <DoctorTendToAnimals.label>Tiere behandeln</DoctorTendToAnimals.label>
  
  <!-- EN: tend to -->
  <DoctorTendToHumanlikes.verb>Patient behandeln</DoctorTendToHumanlikes.verb>
  <!-- EN: tending to -->
  <DoctorTendToHumanlikes.gerund>behandle</DoctorTendToHumanlikes.gerund>
  <!-- EN: tend to patients -->
  <DoctorTendToHumanlikes.label>Patienten behandeln</DoctorTendToHumanlikes.label>
  
  <!-- EN: tend to -->
  <DoctorTendToSelf.verb>Selbst behandeln</DoctorTendToSelf.verb>
  <!-- EN: tending to -->
  <DoctorTendToSelf.gerund>behandle</DoctorTendToSelf.gerund>
  <!-- EN: tend to self -->
  <DoctorTendToSelf.label>Selbst behandeln</DoctorTendToSelf.label>
  
  <!-- EN: do execution on -->
  <DoExecution.verb>exekutieren</DoExecution.verb>
  <!-- EN: doing execution on -->
  <DoExecution.gerund>exekutiere</DoExecution.gerund>
  <!-- EN: execute prisoners -->
  <DoExecution.label>exekutieren</DoExecution.label>
  
  <!-- EN: drill -->
  <Drill.verb>bohren</Drill.verb>
  <!-- EN: drilling -->
  <Drill.gerund>bohre</Drill.gerund>
  <!-- EN: drill at deep drill -->
  <Drill.label>bohren am Tiefenbohrer</Drill.label>
  
  <!-- EN: feed -->
  <FeedPrisoner.verb>versorgen</FeedPrisoner.verb>
  <!-- EN: feeding -->
  <FeedPrisoner.gerund>versorge</FeedPrisoner.gerund>
  <!-- EN: feed prisoners -->
  <FeedPrisoner.label>Gefangene versorgen</FeedPrisoner.label>
  
  <!-- EN: extinguish -->
  <FightFires.verb>Feuer löschen</FightFires.verb>
  <!-- EN: extinguishing -->
  <FightFires.gerund>lösche</FightFires.gerund>
  <!-- EN: fight fires -->
  <FightFires.label>Feuer löschen</FightFires.label>
  
  <!-- EN: fill -->
  <FillFermentingBarrel.verb>befüllen</FillFermentingBarrel.verb>
  <!-- EN: filling -->
  <FillFermentingBarrel.gerund>befülle</FillFermentingBarrel.gerund>
  <!-- EN: fill fermenting barrels -->
  <FillFermentingBarrel.label>Fass befüllen</FillFermentingBarrel.label>
  
  <!-- EN: replace broken components in -->
  <FixBrokenDownBuilding.verb>defekte Bauteile ersetzen</FixBrokenDownBuilding.verb>
  <!-- EN: replacing broken components in -->
  <FixBrokenDownBuilding.gerund>ersetze defekte Bauteile in</FixBrokenDownBuilding.gerund>
  <!-- EN: fix broken-down buildings -->
  <FixBrokenDownBuilding.label>defekte Bauteile in beschädigten Gegenständen ersetzen</FixBrokenDownBuilding.label>
  
  <!-- EN: flick switch on -->
  <Flick.verb>Schalter betätigen</Flick.verb>
  <!-- EN: flicking switch on -->
  <Flick.gerund>betätige Schalter</Flick.gerund>
  <!-- EN: flick switches -->
  <Flick.label>Schalter betätigen</Flick.label>
  
  <!-- EN: harvest -->
  <GrowerHarvest.verb>ernten</GrowerHarvest.verb>
  <!-- EN: harvesting -->
  <GrowerHarvest.gerund>ernte</GrowerHarvest.gerund>
  <!-- EN: harvest crops -->
  <GrowerHarvest.label>Pflanzen ernten</GrowerHarvest.label>
  
  <!-- EN: sow -->
  <GrowerSow.verb>säen</GrowerSow.verb>
  <!-- EN: sowing -->
  <GrowerSow.gerund>säe</GrowerSow.gerund>
  <!-- EN: sow crops -->
  <GrowerSow.label>Pflanzen aussäen</GrowerSow.label>
  
  <!-- EN: feed -->
  <HandlingFeedPatientAnimals.verb>Tier füttern</HandlingFeedPatientAnimals.verb>
  <!-- EN: feeding -->
  <HandlingFeedPatientAnimals.gerund>füttere</HandlingFeedPatientAnimals.gerund>
  <!-- EN: feed animals -->
  <HandlingFeedPatientAnimals.label>Tiere füttern</HandlingFeedPatientAnimals.label>
  
  <!-- EN: haul -->
  <HaulCorpses.verb>tragen</HaulCorpses.verb>
  <!-- EN: hauling -->
  <HaulCorpses.gerund>trage</HaulCorpses.gerund>
  <!-- EN: haul corpses -->
  <HaulCorpses.label>Leichen transportieren</HaulCorpses.label>
  
  <!-- EN: haul -->
  <HaulGeneral.verb>tragen</HaulGeneral.verb>
  <!-- EN: hauling -->
  <HaulGeneral.gerund>trage</HaulGeneral.gerund>
  <!-- EN: haul general things -->
  <HaulGeneral.label>Allgemeine Dinge transportieren</HaulGeneral.label>
  
  <!-- EN: merge -->
  <HaulMerge.verb>Zusammenlegen</HaulMerge.verb>
  <!-- EN: merging -->
  <HaulMerge.gerund>lege zusammen</HaulMerge.gerund>
  <!-- EN: merge things -->
  <HaulMerge.label>Dinge zusammenlegen</HaulMerge.label>
  
  <!-- EN: load -->
  <HelpGatheringItemsForCaravan.verb>beladen</HelpGatheringItemsForCaravan.verb>
  <!-- EN: loading -->
  <HelpGatheringItemsForCaravan.gerund>belade</HelpGatheringItemsForCaravan.gerund>
  <!-- EN: load caravan -->
  <HelpGatheringItemsForCaravan.label>Karawane beladen</HelpGatheringItemsForCaravan.label>
  
  <!-- EN: hunt -->
  <HunterHunt.verb>jagen</HunterHunt.verb>
  <!-- EN: hunting -->
  <HunterHunt.gerund>jage</HunterHunt.gerund>
  <!-- EN: hunt -->
  <HunterHunt.label>jagen</HunterHunt.label>
  
  <!-- EN: load -->
  <LoadTransporters.verb>beladen</LoadTransporters.verb>
  <!-- EN: loading -->
  <LoadTransporters.gerund>belade</LoadTransporters.gerund>
  <!-- EN: load transporters -->
  <LoadTransporters.label>Transporter beladen</LoadTransporters.label>
  
  <!-- EN: milk -->
  <Milk.verb>melken</Milk.verb>
  <!-- EN: milking -->
  <Milk.gerund>melke</Milk.gerund>
  <!-- EN: milk animals -->
  <Milk.label>Tiere melken</Milk.label>
  
  <!-- EN: mine -->
  <Mine.verb>abbauen</Mine.verb>
  <!-- EN: mining -->
  <Mine.gerund>bau ab</Mine.gerund>
  <!-- EN: mine -->
  <Mine.label>abbauen</Mine.label>
  
  <!-- EN: open -->
  <Open.verb>öffnen</Open.verb>
  <!-- EN: opening -->
  <Open.gerund>öffne</Open.gerund>
  <!-- EN: open containers -->
  <Open.label>Behälter öffnen</Open.label>
  
  <!-- EN: receive treatment in -->
  <PatientGoToBedEmergencyTreatment.verb>Behandlung erhalten in</PatientGoToBedEmergencyTreatment.verb>
  <!-- EN: receiving treatment in -->
  <PatientGoToBedEmergencyTreatment.gerund>erhalte Behandlung in</PatientGoToBedEmergencyTreatment.gerund>
  <!-- EN: go to bed for emergency treatment -->
  <PatientGoToBedEmergencyTreatment.label>Gehe ins Bett, um Notfall-Behandlung zu erhalten</PatientGoToBedEmergencyTreatment.label>
  
  <!-- EN: get bed rest in -->
  <PatientGoToBedRecuperate.verb>im Bett erholen</PatientGoToBedRecuperate.verb>
  <!-- EN: getting bed rest in -->
  <PatientGoToBedRecuperate.gerund>erhole Dich in</PatientGoToBedRecuperate.gerund>
  <!-- EN: recuperate in bed -->
  <PatientGoToBedRecuperate.label>erholen im Bett</PatientGoToBedRecuperate.label>
  
  <!-- EN: receive treatment in -->
  <PatientGoToBedTreatment.verb>Behandlung erhalten in</PatientGoToBedTreatment.verb>
  <!-- EN: receiving treatment in -->
  <PatientGoToBedTreatment.gerund>erhalte Behandlung in</PatientGoToBedTreatment.gerund>
  <!-- EN: go to bed for treatment -->
  <PatientGoToBedTreatment.label>Gehe ins Bett, um Behandlung zu erhalten</PatientGoToBedTreatment.label>
  
  <!-- EN: cut -->
  <PlantsCut.verb>schneiden</PlantsCut.verb>
  <!-- EN: cutting -->
  <PlantsCut.gerund>schneide</PlantsCut.gerund>
  <!-- EN: cut plants -->
  <PlantsCut.label>Pflanzen schneiden</PlantsCut.label>
  
  <!-- EN: rearm -->
  <RearmTraps.verb>Falle reaktivieren</RearmTraps.verb>
  <!-- EN: rearming -->
  <RearmTraps.gerund>reaktiviere Falle</RearmTraps.gerund>
  <!-- EN: rearm traps -->
  <RearmTraps.label>Fallen reaktivieren</RearmTraps.label>
  
  <!-- EN: rearm -->
  <RearmTurrets.verb>Geschütz erneuern</RearmTurrets.verb>
  <!-- EN: rearming -->
  <RearmTurrets.gerund>erneuere Geschütz</RearmTurrets.gerund>
  <!-- EN: rearm turrets -->
  <RearmTurrets.label>Geschütz erneuern</RearmTurrets.label>
  
  <!-- EN: refuel -->
  <Refuel.verb>auffüllen</Refuel.verb>
  <!-- EN: refueling -->
  <Refuel.gerund>fülle auf</Refuel.gerund>
  <!-- EN: refuel fuelable buildings -->
  <Refuel.label>auffüllbare Gebäude auffüllen</Refuel.label>
  
  <!-- EN: release -->
  <ReleasePrisoner.verb>Gefangenen freilassen</ReleasePrisoner.verb>
  <!-- EN: releasing -->
  <ReleasePrisoner.gerund>lass Gefangenen frei</ReleasePrisoner.gerund>
  <!-- EN: release prisoners -->
  <ReleasePrisoner.label>Gefangene freilassen</ReleasePrisoner.label>
  
  <!-- EN: remove roof -->
  <RemoveRoofs.verb>Dächer entfernen</RemoveRoofs.verb>
  <!-- EN: removing roof -->
  <RemoveRoofs.gerund>entferne Dächer</RemoveRoofs.gerund>
  <!-- EN: remove roofs -->
  <RemoveRoofs.label>Dächer entfernen</RemoveRoofs.label>
  
  <!-- EN: repair -->
  <Repair.verb>reparieren</Repair.verb>
  <!-- EN: repairing -->
  <Repair.gerund>repariere</Repair.gerund>
  <!-- EN: repair damaged things -->
  <Repair.label>beschädigte Gegenstände reparieren</Repair.label>
  
  <!-- EN: research -->
  <Research.verb>forschen</Research.verb>
  <!-- EN: researching at -->
  <Research.gerund>forsche</Research.gerund>
  <!-- EN: do research -->
  <Research.label>erforschen</Research.label>
  
  <!-- EN: scan -->
  <Scan.verb>scannen</Scan.verb>
  <!-- EN: scanning at -->
  <Scan.gerund>scanne</Scan.gerund>
  <!-- EN: operate scanner -->
  <Scan.label>Scanner bedienen</Scan.label>
  
  <!-- EN: shear -->
  <Shear.verb>scheren</Shear.verb>
  <!-- EN: shearing -->
  <Shear.gerund>schere</Shear.gerund>
  <!-- EN: shear animals -->
  <Shear.label>Tiere scheren</Shear.label>
  
  <!-- EN: slaughter -->
  <Slaughter.verb>schlachten</Slaughter.verb>
  <!-- EN: slaughtering -->
  <Slaughter.gerund>schlachte</Slaughter.gerund>
  <!-- EN: slaughter animals -->
  <Slaughter.label>Tiere schlachten</Slaughter.label>
  
  <!-- EN: strip -->
  <Strip.verb>ausziehen</Strip.verb>
  <!-- EN: stripping -->
  <Strip.gerund>ausziehen</Strip.gerund>
  <!-- EN: strip corpses -->
  <Strip.label>Leichen ausziehen</Strip.label>
  
  <!-- EN: take beer -->
  <TakeBeerOutOfFermentingBarrel.verb>Bier aus Fass holen</TakeBeerOutOfFermentingBarrel.verb>
  <!-- EN: taking beer from -->
  <TakeBeerOutOfFermentingBarrel.gerund>hole Bier aus Fass</TakeBeerOutOfFermentingBarrel.gerund>
  <!-- EN: take beer out of fermenting barrels -->
  <TakeBeerOutOfFermentingBarrel.label>Bier aus Fass holen</TakeBeerOutOfFermentingBarrel.label>
  
  <!-- EN: take to bed -->
  <TakePrisonerToBed.verb>ins Bett bringen</TakePrisonerToBed.verb>
  <!-- EN: taking to bed -->
  <TakePrisonerToBed.gerund>bring ins Bett</TakePrisonerToBed.gerund>
  <!-- EN: take prisoners to bed -->
  <TakePrisonerToBed.label>Gefangene ins Bett bringen</TakePrisonerToBed.label>
  
  <!-- EN: take to operate -->
  <TakeToBedToOperate.verb>zur Operation bringen</TakeToBedToOperate.verb>
  <!-- EN: taking to operate -->
  <TakeToBedToOperate.gerund>bringe zur Operation</TakeToBedToOperate.gerund>
  <!-- EN: take patients to bed for operations -->
  <TakeToBedToOperate.label>Patienten zum Operationsort bringen</TakeToBedToOperate.label>
  
  <!-- EN: tame -->
  <Tame.verb>zähmen</Tame.verb>
  <!-- EN: taming -->
  <Tame.gerund>zähme</Tame.gerund>
  <!-- EN: tame animals -->
  <Tame.label>Tiere zähmen</Tame.label>
  
  <!-- EN: train -->
  <Train.verb>trainieren</Train.verb>
  <!-- EN: training -->
  <Train.gerund>trainiere</Train.gerund>
  <!-- EN: train animals -->
  <Train.label>Tiere trainieren</Train.label>
  
  <!-- EN: uninstall -->
  <Uninstall.verb>deinstallieren</Uninstall.verb>
  <!-- EN: uninstalling -->
  <Uninstall.gerund>deinstalliere</Uninstall.gerund>
  <!-- EN: uninstall structures -->
  <Uninstall.label>Strukturen deinstallieren</Uninstall.label>
  
  <!-- EN: unload -->
  <UnloadCarriers.verb>entladen</UnloadCarriers.verb>
  <!-- EN: unloading -->
  <UnloadCarriers.gerund>entlade</UnloadCarriers.gerund>
  <!-- EN: unload carriers -->
  <UnloadCarriers.label>Träger entladen</UnloadCarriers.label>
  
  <!-- EN: visit -->
  <VisitSickPawn.verb>Patient besuchen</VisitSickPawn.verb>
  <!-- EN: visiting -->
  <VisitSickPawn.gerund>besuche</VisitSickPawn.gerund>
  <!-- EN: visit sick people -->
  <VisitSickPawn.label>kranke Patienten besuchen</VisitSickPawn.label>
  
</LanguageData>