<?xml version="1.0" encoding="UTF-8"?>
<LanguageData>

	<!-- =========================== World conditions =======================-->

	<Eclipse.label>Sonnenfinsternis</Eclipse.label>
	<Eclipse.letterLabel>Sonnenfinsternis</Eclipse.letterLabel>
	<Eclipse.letterText>Einer der Monde des Planeten verdeckt die Sonne. Eine Sonnenfinsternis hat begonnen.</Eclipse.letterText>

	<SolarFlare.label>Sonneneruption</SolarFlare.label>
	<SolarFlare.letterLabel>Sonneneruption</SolarFlare.letterLabel>
	<SolarFlare.letterText>Eine Sonneneruption hat begonnen.\n\nDie starke Strahlung macht alle elektrischen Geräte unbrauchbar.\n\nEs sollte in etwa einem Tag wieder vorbei sein.</SolarFlare.letterText>

</LanguageData>
